BottleSessions/BottleSessions.py
BottleSessions/Session.py
BottleSessions/__init__.py
BottleSessions/backing.py
BottleSessions-21.9.21.dist-info/License.txt
BottleSessions-21.9.21.dist-info/METADATA
BottleSessions-21.9.21.dist-info/WHEEL
BottleSessions-21.9.21.dist-info/top_level.txt
BottleSessions-21.9.21.dist-info/RECORD
