Metadata-Version: 2.1
Name: BottleSessions
Version: 21.9.21
Summary: Sessions middleware plug-in for Bottle
Home-page: https://github.com/Glocktober/BottleSessions
Author: gunville
Author-email: rk13088@yahoo.com
License: UNKNOWN
Project-URL: repo, https://github.com/Glocktober/BottleSessions
Project-URL: overview, https://github.com/Glocktober/BottleSessions/blob/main/README.md
Keywords: 'bottle cachelib sessions redis memcached'
Platform: UNKNOWN
Classifier: Programming Language :: Python :: 3
Classifier: License :: OSI Approved :: MIT License
Classifier: Operating System :: OS Independent
Classifier: Framework :: Bottle
Requires-Python: >=3.6
License-File: License.txt
Requires-Dist: bottle (>=0.12.0)
Requires-Dist: cachelib (>=0.2.0)
